request_curl/__init__.py
request_curl/defaults.py
request_curl/dict.py
request_curl/helper.py
request_curl/models.py
request_curl/sessions.py
request_curl-0.0.3.dist-info/METADATA
request_curl-0.0.3.dist-info/WHEEL
request_curl-0.0.3.dist-info/LICENSE
request_curl-0.0.3.dist-info/RECORD
